_stack.cp39-win_amd64.pyd
sstack/__init__.py
sstack-0.0.1.dist-info/LICENSE
sstack-0.0.1.dist-info/METADATA
sstack-0.0.1.dist-info/WHEEL
sstack-0.0.1.dist-info/top_level.txt
sstack-0.0.1.dist-info/RECORD
